jsonhome-0.1.0.dist-info/metadata.json
jsonhome-0.1.0.dist-info/pbr.json
jsonhome-0.1.0.dist-info/top_level.txt
jsonhome-0.1.0.dist-info/RECORD
jsonhome-0.1.0.dist-info/DESCRIPTION.rst
jsonhome-0.1.0.dist-info/METADATA
jsonhome-0.1.0.dist-info/WHEEL
jsonhome/__init__.py
jsonhome/tests/base.py
jsonhome/tests/test_document.py
jsonhome/tests/__init__.py
jsonhome/tests/test_resource.py
